jacobi_driver_fanuc.cpython-312-x86_64-linux-gnu.so
libjacobi-fanuc-driver.so
jacobi_fanuc_driver.libs/libboost_system-69a6c43e.so.1.66.0
jacobi_fanuc_driver-1.1.21.dist-info/METADATA
jacobi_fanuc_driver-1.1.21.dist-info/WHEEL
jacobi_fanuc_driver-1.1.21.dist-info/RECORD
jacobi_fanuc_driver-1.1.21.dist-info/licenses/LICENSE
