Metadata-Version: 2.2
Name: jacobi-fanuc-driver
Version: 1.1.21
Summary: Driver for FANUC Robots.
Keywords: robotics,robot-driver,driver,fanuc
Author-Email: Jacobi Robotics <lars.berscheid@jacobirobotics.com>
License: Copyright (c) 2022-2024 Jacobi Robotics Inc.
Classifier: Development Status :: 3 - Alpha
Classifier: Intended Audience :: Science/Research
Classifier: Topic :: Scientific/Engineering
Classifier: License :: Other/Proprietary License
Classifier: Programming Language :: C++
Project-URL: homepage, https://www.jacobirobotics.com
Project-URL: documentation, https://docs.jacobirobotics.com
Requires-Python: >=3.10
Requires-Dist: jacobi-motion>=1.1.21
